pod_virtual_account/__init__.py
pod_virtual_account/json_schema.json
pod_virtual_account/pod_virtual_account.py
pod_virtual_account/services.json
pod_virtual_account/version.py
pod_virtual_account/withdraw_type.py
pod_virtual_account-1.0.0.dist-info/METADATA
pod_virtual_account-1.0.0.dist-info/WHEEL
pod_virtual_account-1.0.0.dist-info/top_level.txt
pod_virtual_account-1.0.0.dist-info/RECORD
